PyQt6/sip.cp311-win_arm64.pyd
PyQt6_sip-13.9.1.dist-info/LICENSE
PyQt6_sip-13.9.1.dist-info/METADATA
PyQt6_sip-13.9.1.dist-info/WHEEL
PyQt6_sip-13.9.1.dist-info/top_level.txt
PyQt6_sip-13.9.1.dist-info/RECORD
