Metadata-Version: 2.1
Name: PyQt6_sip
Version: 13.9.1
Summary: The sip module support for PyQt6
Home-page: https://github.com/Python-SIP/sip
Author: Phil Thompson
Author-email: phil@riverbankcomputing.com
License: SIP
Platform: X11
Platform: macOS
Platform: Windows
Requires-Python: >=3.9
License-File: LICENSE
